DESCRIPTION.rst
MANIFEST.in
README.rst
setup.cfg
setup.py
perceptual/__init__.py
perceptual/filterbank.py
perceptual/metric.py
perceptual.egg-info/PKG-INFO
perceptual.egg-info/SOURCES.txt
perceptual.egg-info/dependency_links.txt
perceptual.egg-info/top_level.txt