Metadata-Version: 1.1
Name: perceptual
Version: 0.1
Summary: Steerable pyramid
Home-page: https://github.com/andreydung/Steerable-filter
Author: Dzung Nguyen
Author-email: dzungng89@gmail.com
License: MIT
Download-URL: https://github.com/andreydung/Steerable-filter/tarball/0.1
Keywords: image processing
Platform: UNKNOWN
